pyloci/__init__.py
pyloci/generate_contains_counts_using_api.py
pyloci/generate_loci_rdf_testdata.py
pyloci/generate_overlaps_using_api.py
pyloci/reapportioning.py
pyloci/api/__init__.py
pyloci/api/util.py
pyloci/exporter/__init__.py
pyloci/exporter/helpers.py
pyloci/exporter/asgs/__init__.py
pyloci/exporter/asgs/export_asgs_features.py
pyloci/exporter/asgs_geofabric/__init__.py
pyloci/exporter/asgs_geofabric/meshblock_catchments.py
pyloci/sparql/__init__.py
pyloci/sparql/generate_loci_contains_testdata.py
pyloci/sparql/generate_loci_mb16cc_relations_testdata.py
pyloci/sparql/generate_loci_reapportioning_testdata.py
pyloci/sparql/generate_loci_type_count.py
pyloci/sparql/generate_loci_uri_to_id_mappings.py
pyloci/sparql/generate_loci_withins_testdata.py
pyloci/sparql/query_loci_location_labels.py
pyloci/sparql/query_loci_mb16cc_contains.py
pyloci/sparql/query_loci_reapportioning.py
pyloci/sparql/query_loci_thing.py
pyloci/sparql/util.py
pyloci-0.1.2.dist-info/LICENSE.txt
pyloci-0.1.2.dist-info/METADATA
pyloci-0.1.2.dist-info/WHEEL
pyloci-0.1.2.dist-info/top_level.txt
pyloci-0.1.2.dist-info/RECORD
