Metadata-Version: 2.1
Name: pyloci
Version: 0.1.2
Summary: Python library for Loc-I
Home-page: https://locationindex.org/
Author: Location Index
Author-email: locationindex@ga.gov.au
License: MIT
Platform: UNKNOWN
Classifier: Programming Language :: Python :: 3
Classifier: License :: OSI Approved :: MIT License
Classifier: Operating System :: OS Independent
Classifier: Development Status :: 3 - Alpha
Requires-Python: >=3.3
Requires-Dist: XlsxWriter
Requires-Dist: SPARQLWrapper (<=1.8.5)
Requires-Dist: rdflib (<=4.2.2)
Requires-Dist: python-dotenv (<=0.11.0)
Requires-Dist: requests (<=2.23.0)
